videogit/__init__.py
videogit/videogit.py
VideoGit-0.1.0.dist-info/LICENSE.txt
VideoGit-0.1.0.dist-info/METADATA
VideoGit-0.1.0.dist-info/WHEEL
VideoGit-0.1.0.dist-info/entry_points.txt
VideoGit-0.1.0.dist-info/top_level.txt
VideoGit-0.1.0.dist-info/RECORD
