Metadata-Version: 2.1
Name: VideoGit
Version: 0.1.0
Summary: Convert git commit history, to a animated beautiful coding video.
Home-page: https://github.com/shahanneda/videogit
Author: Shahan Neda
Author-email: shahan.neda@gmail.com
License: UNKNOWN
Platform: UNKNOWN
Classifier: Programming Language :: Python :: 3
Classifier: License :: OSI Approved :: MIT License
Classifier: Operating System :: OS Independent
Requires-Python: >=3.6
Requires-Dist: termcolor
